Workbook

Sheet Cover
A1: U.S. Pharmaceutical Exporter — FX Transaction Hedge Model
A2: EUR 8,000,000 receivable due in 365 days · Scenario slug: pharma-exporter
A4: FIN-321 International Finance & Securities — Stage 3 Build
A6: Scenario | B6: pharma-exporter
A7: Exposure | B7: EUR 8,000,000 receivable (customer AR, EU sales)
A8: Author | B8: Allan Jay Badua
A9: Date built | B9: 2026-08-07
A10: Spec source | B10: docs/specs/2026-08-07-Badua-pharma-exporter-spec.md
A11: Workbook version | B11: 1.1
A12: Build method | B12: AI-assisted (Claude), openpyxl; audited by hand — see analysis/2026-08-07-Badua-build-audit.md
A14: Data Provenance
A15: Named Range | B15: Placeholder Value | C15: Status | D15: Phase-4 Source
A16: FC_AMT | B16: EUR 8,000,000 | C16: Firm (contract amount) | D16: Sales contract / AR aging schedule
A17: S0_in | B17: 1.1525 USD/EUR | C17: Live (2026-08-07) | D17: Yahoo Finance EURUSD=X, 2026-08-07 23:01:54 GMT+1
A18: F0_in | B18: derived (parity) | C18: Live (derived, CIP) | D18: CIP-implied from live S0_in, R_USD, R_FC (no live outright 1Y quote found in free sources); see market-data memo for comparison to indicative placeholder
A19: R_USD | B19: 4.01% | C19: Live (2026-08-07) | D19: US Treasury Daily Par Yield Curve, 1 Yr CMT
A20: R_FC | B20: 2.884% | C20: Live (2026-08-06, most recent published fixing) | D20: 12M Euribor (EMMI via euribor-rates.eu, 24h-delayed publication)
A21: K_PUT | B21: 1.1525 (ATM) | C21: Live (set to live S0_in) | D21: Desk quote at strike selection
A22: PREM_PUT | B22: 0.0210 USD/EUR | C22: Assumption — scenario-given premium retained (no live OTC quote pulled) | D22: OTC dealer quote / Bloomberg OVML
A23: K_CALL | B23: 1.1525 (ATM, placeholder) | C23: Live (set to live S0_in) — added for build-contract completeness; not used in the receivable decision | D23: Desk quote at strike selection
A24: PREM_CALL | B24: derived (put-call parity, placeholder) | C24: Indicative — added for build-contract completeness; not used in the receivable decision | D24: OTC dealer quote / Bloomberg OVML
A25: T_DAYS | B25: 365 | C25: Firm (contract term) | D25: Contract settlement date minus build date
A27: Note: K_CALL / PREM_CALL are placeholders. This scenario is receivable-only; the Options-Call tab exists to satisfy the build contract's put-and-call requirement and named-range completeness, not because a call hedge is recommended here.

Sheet Legend-Key
A1: Legend / Key
A2: Color convention applied throughout this workbook
A4: Color | B4: Meaning
B5: Yellow = Inputs — hardcoded, analyst-editable assumptions and market quotes
B7: Blue = Assumptions — modeling conventions (day-count basis, step size) rarely changed
B9: Green = Formulas — every calculated cell; always references named ranges, never a bare cell address
B11: Gray = Outputs — final summary results meant for an executive read (strategy summary, validation checks)
A14: Named-Range Index
A15: Named Range | B15: Sheet!Cell | C15: Description
A16: FC_AMT | B16: Inputs!C5 | C16: Foreign-currency notional (EUR receivable)
A17: S0_in | B17: Inputs!C6 | C17: Spot exchange rate at inception (USD per EUR)
A18: R_USD | B18: Inputs!C7 | C18: USD interest rate to settlement
A19: R_FC | B19: Inputs!C8 | C19: EUR interest rate to settlement
A20: T_DAYS | B20: Inputs!C9 | C20: Days to settlement
A21: BASIS_USD | B21: Inputs!C10 | C21: USD day-count denominator (ACT/360)
A22: BASIS_FC | B22: Inputs!C11 | C22: EUR day-count denominator (ACT/365)
A23: STEP_FRAC | B23: Inputs!C12 | C23: Sensitivity grid step size (1%)
A24: DF_USD | B24: Inputs!C13 | C24: USD accumulation factor
A25: DF_FC | B25: Inputs!C14 | C25: EUR accumulation factor
A26: F0_in | B26: Inputs!C15 | C26: Forward rate to settlement (derived, indicative)
... A36: USD_CEILING_CALL | B36: Options_Call!C10 | C36: Best-case (ceiling) call outcome across the grid
A38: Bold names above (FC_AMT through T_DAYS core set) are the ten named ranges required by the build contract: FC_AMT, S0_in, F0_in, R_USD, R_FC, K_PUT, K_CALL, PREM_PUT, PREM_CALL, T_DAYS.

Sheet Inputs
A1: Inputs
A2: Named-range contract — the only tab an analyst edits for scenario work
A4: Named Range | B4: Description | C4: Value | D4: Unit | E4: Category | F4: Source / Notes
A5: FC_AMT | B5: Foreign-currency notional (EUR receivable) | C5: 8000000 | D5: EUR | E5: Input | F5: Sales contract / AR aging schedule
A6: S0_in | B6: Spot exchange rate at inception | C6: 1.1525 | D6: USD/EUR | E6: Input | F6: Yahoo Finance EURUSD=X, live quote as of 2026-08-07 23:01:54 GMT+1 (1.1525; day range 1.1523-1.1526; prev close 1.1555)
A7: R_USD | B7: USD interest rate to settlement | C7: 0.0401 | D7: Annual % | E7: Input | F7: US Treasury Daily Par Yield Curve, 1 Yr CMT, 2026-08-07 (4.01%) — chosen over SOFR for a clean, freely available, official USD risk-free benchmark at the 1Y tenor
A8: R_FC | B8: EUR interest rate to settlement | C8: 0.02884 | D8: Annual % | E8: Input | F8: 12M Euribor, EMMI (via euribor-rates.eu, delayed 24h), most recent published fixing 2026-08-06 (2.884%) — chosen as the standard EUR-leg 1Y interbank reference matching R_USD tenor/purpose
A9: T_DAYS | B9: Days to settlement | C9: 365 | D9: Days | E9: Input | F9: Contract settlement date minus build date
A10: BASIS_USD | B10: USD-leg day-count denominator | C10: 360 | D10: Days | E10: Assumption | F10: Market convention (ACT/360)
A11: BASIS_FC | B11: EUR-leg day-count denominator | C11: 365 | D11: Days | E11: Assumption | F11: Market convention (ACT/365)
A12: STEP_FRAC | B12: Sensitivity grid step size | C12: 0.01 | D12: % of S0_in | E12: Assumption | F12: Drives an even ±5% grid in 1% steps (§6)
A13: DF_USD | B13: USD accumulation factor to settlement | C13: =1+R_USD*T_DAYS/BASIS_USD -> 1.0406569 | D13: factor | E13: Formula | F13: Note: 1 + R_USD × T_DAYS / BASIS_USD
A14: DF_FC | B14: EUR accumulation factor to settlement | C14: =1+R_FC*T_DAYS/BASIS_FC -> 1.02884 | D14: factor | E14: Formula | F14: Note: 1 + R_FC × T_DAYS / BASIS_FC
A15: F0_in | B15: Forward rate to settlement (365 days) | C15: =S0_in*DF_USD/DF_FC -> 1.1657373 | D15: USD/EUR | E15: Formula | F15: Note: S0_in × DF_USD / DF_FC (indicative; live quote at Phase 4)
A16: K_PUT | B16: Put option strike | C16: 1.1525 | D16: USD/EUR | E16: Input | F16: Set to live S0_in (ATM) per scenario strike convention; desk quote proxy
A17: PREM_PUT | B17: Put premium, USD per 1 EUR | C17: 0.021 | D17: USD | E17: Input | F17: Scenario-given premium retained as an assumption (see market-data memo) — no live OTC quote pulled
A18: FV_PREM_PUT | B18: Future value of put premium at settlement | C18: =-PREM_PUT*FC_AMT*DF_USD -> -174830.37 | D18: USD | E18: Formula | F18: Note: −PREM_PUT × FC_AMT × DF_USD
A19: K_CALL | B19: Call option strike (indicative placeholder) | C19: 1.1525 | D19: USD/EUR | E19: Input | F19: Set to live S0_in (ATM placeholder); build-contract completeness only, not used in receivable decision
A20: PREM_CALL | B20: Call premium, USD per 1 EUR (indicative placeholder) | C20: =PREM_PUT+(F0_in-K_CALL)/DF_USD -> 0.033720105 | D20: USD | E20: Formula | F20: Note: PREM_PUT + (F0_in − K_CALL) / DF_USD (put-call parity)
A21: FV_PREM_CALL | B21: Future value of call premium at settlement | C21: =-PREM_CALL*FC_AMT*DF_USD -> -280728.49 | D21: USD | E21: Formula | F21: Note: −PREM_CALL × FC_AMT × DF_USD

Sheet Forward
A1: Forward Hedge
A2: Contract today to sell EUR at a locked rate on the settlement date
A4: Mechanics
A5: Sell EUR forward today at F0_in; USD proceeds are locked in and invariant to the settlement-date spot rate.
A8: USD_FWD = FC_AMT × F0_in
A9: USD_FWD (locked-in USD proceeds) | C9: =FC_AMT*F0_in -> 9325898.1
A11: Note: this figure is invariant across the S_T sensitivity grid — that is the point of a forward.

Sheet MoneyMarket
A1: Money-Market Hedge
A2: Borrow EUR today, convert at spot, invest the USD — a synthetic forward
A4: Step 1 — Borrow EUR today
A5: EUR_BORROWED = FC_AMT / DF_FC | C5: =FC_AMT/DF_FC -> 7775747.4
A7: Step 2 — Convert to USD at spot
A8: USD_CONVERTED = EUR_BORROWED × S0_in | C8: =EUR_BORROWED*S0_in -> 8961548.9
A10: Step 3 — Invest the USD to maturity
A11: USD_MM = USD_CONVERTED × DF_USD | C11: =USD_CONVERTED*DF_USD -> 9325898.1
A13: Parity Check
A14: USD_MM − USD_FWD | C14: =USD_MM-USD_FWD -> 0
A15: % difference | C15: =(USD_MM-USD_FWD)/USD_FWD -> 0
A16: Parity check (pass if within 0.05%) | C16: =IF(ABS(C15)<=0.0005,"PASS","FAIL") -> PASS

Sheet Options_Put
A1: Option Hedge — Put (Floor with Upside)
A2: Buy the right, not the obligation, to sell EUR at K_PUT
A4: Payoff function (applies to every S_T on the Sensitivity grid)
A5: USD_PUT(S_T) = MAX(S_T, K_PUT) × FC_AMT + FV_PREM_PUT
A7: Premium paid today = PREM_PUT × FC_AMT | C7: =PREM_PUT*FC_AMT -> 168000
A9: Baseline (S_T = S0_in) | C9: =MAX(S0_in,K_PUT)*FC_AMT+FV_PREM_PUT -> 9045169.6
A10: USD_FLOOR_PUT = MIN across S_T grid | C10: =MIN(Sensitivity!F5:F15) -> 9045169.6
A12: Kink verification: at S_T = K_PUT, USD_PUT should equal K_PUT × FC_AMT + FV_PREM_PUT exactly.
A13: Kink check (baseline row, since K_PUT = S0_in) | C13: =IF(ABS(Sensitivity!F10-(K_PUT*FC_AMT+FV_PREM_PUT))<0.01,"PASS","FAIL") -> PASS

Sheet Options_Call
A1: Option Hedge — Call (placeholder, architecture symmetry)
A2: Not used in the receivable recommendation — built to satisfy the put-and-call build contract
A4: This scenario is a EUR receivable; the protective option family is the put (Options_Put tab). This tab exists so the K_CALL / PREM_CALL named ranges are attached to live formulas and a call payoff is computed as a function of S_T, per the build contract.
A6: Payoff function (applies to every S_T on the Sensitivity grid)
A7: USD_CALL(S_T) = MIN(S_T, K_CALL) × FC_AMT + FV_PREM_CALL
A9: Premium paid today = PREM_CALL × FC_AMT | C9: =PREM_CALL*FC_AMT -> 269760.84
A11: Baseline (S_T = S0_in) | C11: =MIN(S0_in,K_CALL)*FC_AMT+FV_PREM_CALL -> 8939271.5
A12: USD_CEILING_CALL = MAX across S_T grid | C12: =MAX(Sensitivity!G5:G15) -> 8939271.5

Sheet Sensitivity
A1: Sensitivity Table
A2: S_T grid: S0_in × (1 ± 5%) in 1% steps, formula-driven — no hand-typed rows
A4: n | B4: S_T | C4: USD_NO_HEDGE | D4: USD_FWD | E4: USD_MM | F4: USD_PUT | G4: USD_CALL | H4: HP_Forward | I4: HP_MoneyMkt | J4: HP_Put | K4: Winner (all) | L4: Best active hedge
A5: -5 | B5: =S0_in*(1+A5*STEP_FRAC) -> 1.094875 | C5: =B5*FC_AMT -> 8759000 | D5: =USD_FWD -> 9325898.1 | E5: =USD_MM -> 9325898.1 | F5: =MAX(B5,K_PUT)*FC_AMT+FV_PREM_PUT -> 9045169.6 | G5: =MIN(B5,K_CALL)*FC_AMT+FV_PREM_CALL -> 8478271.5 | H5: =D5-C5 -> 566898.13 | I5: =E5-C5 -> 566898.13 | J5: =F5-C5 -> 286169.63 | K5: =IF(C5=MAX(C5,D5,E5,F5),"No Hedge",IF(D5=MAX(C5,D5,E5,F5),"Forward",IF(E5=MAX(C5,D5,E5,F5),"Money Market","Put"))) -> Forward | L5: =IF(D5=MAX(D5,E5,F5),"Forward",IF(E5=MAX(D5,E5,F5),"Money Market","Put")) -> Forward
A6: -4 | B6: =S0_in*(1+A6*STEP_FRAC) -> 1.1064 | C6: =B6*FC_AMT -> 8851200 | D6: =USD_FWD -> 9325898.1 | E6: =USD_MM -> 9325898.1 | F6: =MAX(B6,K_PUT)*FC_AMT+FV_PREM_PUT -> 9045169.6 | G6: =MIN(B6,K_CALL)*FC_AMT+FV_PREM_CALL -> 8570471.5 | H6: =D6-C6 -> 474698.13 | I6: =E6-C6 -> 474698.13 | J6: =F6-C6 -> 193969.63 | K6: =IF(C6=MAX(C6,D6,E6,F6),"No Hedge",IF(D6=MAX(C6,D6,E6,F6),"Forward",IF(E6=MAX(C6,D6,E6,F6),"Money Market","Put"))) -> Forward | L6: =IF(D6=MAX(D6,E6,F6),"Forward",IF(E6=MAX(D6,E6,F6),"Money Market","Put")) -> Forward
A7: -3 | B7: =S0_in*(1+A7*STEP_FRAC) -> 1.117925 | C7: =B7*FC_AMT -> 8943400 | D7: =USD_FWD -> 9325898.1 | E7: =USD_MM -> 9325898.1 | F7: =MAX(B7,K_PUT)*FC_AMT+FV_PREM_PUT -> 9045169.6 | G7: =MIN(B7,K_CALL)*FC_AMT+FV_PREM_CALL -> 8662671.5 | H7: =D7-C7 -> 382498.13 | I7: =E7-C7 -> 382498.13 | J7: =F7-C7 -> 101769.63 | K7: =IF(C7=MAX(C7,D7,E7,F7),"No Hedge",IF(D7=MAX(C7,D7,E7,F7),"Forward",IF(E7=MAX(C7,D7,E7,F7),"Money Market","Put"))) -> Forward | L7: =IF(D7=MAX(D7,E7,F7),"Forward",IF(E7=MAX(D7,E7,F7),"Money Market","Put")) -> Forward
A8: -2 | B8: =S0_in*(1+A8*STEP_FRAC) -> 1.12945 | C8: =B8*FC_AMT -> 9035600 | D8: =USD_FWD -> 9325898.1 | E8: =USD_MM -> 9325898.1 | F8: =MAX(B8,K_PUT)*FC_AMT+FV_PREM_PUT -> 9045169.6 | G8: =MIN(B8,K_CALL)*FC_AMT+FV_PREM_CALL -> 8754871.5 | H8: =D8-C8 -> 290298.13 | I8: =E8-C8 -> 290298.13 | J8: =F8-C8 -> 9569.6333 | K8: =IF(C8=MAX(C8,D8,E8,F8),"No Hedge",IF(D8=MAX(C8,D8,E8,F8),"Forward",IF(E8=MAX(C8,D8,E8,F8),"Money Market","Put"))) -> Forward | L8: =IF(D8=MAX(D8,E8,F8),"Forward",IF(E8=MAX(D8,E8,F8),"Money Market","Put")) -> Forward
A9: -1 | B9: =S0_in*(1+A9*STEP_FRAC) -> 1.140975 | C9: =B9*FC_AMT -> 9127800 | D9: =USD_FWD -> 9325898.1 | E9: =USD_MM -> 9325898.1 | F9: =MAX(B9,K_PUT)*FC_AMT+FV_PREM_PUT -> 9045169.6 | G9: =MIN(B9,K_CALL)*FC_AMT+FV_PREM_CALL -> 8847071.5 | H9: =D9-C9 -> 198098.13 | I9: =E9-C9 -> 198098.13 | J9: =F9-C9 -> -82630.367 | K9: =IF(C9=MAX(C9,D9,E9,F9),"No Hedge",IF(D9=MAX(C9,D9,E9,F9),"Forward",IF(E9=MAX(C9,D9,E9,F9),"Money Market","Put"))) -> Forward | L9: =IF(D9=MAX(D9,E9,F9),"Forward",IF(E9=MAX(D9,E9,F9),"Money Market","Put")) -> Forward
A10: 0 | B10: =S0_in*(1+A10*STEP_FRAC) -> 1.1525 | C10: =B10*FC_AMT -> 9220000 | D10: =USD_FWD -> 9325898.1 | E10: =USD_MM -> 9325898.1 | F10: =MAX(B10,K_PUT)*FC_AMT+FV_PREM_PUT -> 9045169.6 | G10: =MIN(B10,K_CALL)*FC_AMT+FV_PREM_CALL -> 8939271.5 | H10: =D10-C10 -> 105898.13 | I10: =E10-C10 -> 105898.13 | J10: =F10-C10 -> -174830.37 | K10: =IF(C10=MAX(C10,D10,E10,F10),"No Hedge",IF(D10=MAX(C10,D10,E10,F10),"Forward",IF(E10=MAX(C10,D10,E10,F10),"Money Market","Put"))) -> Forward | L10: =IF(D10=MAX(D10,E10,F10),"Forward",IF(E10=MAX(D10,E10,F10),"Money Market","Put")) -> Forward
A11: 1 | B11: =S0_in*(1+A11*STEP_FRAC) -> 1.164025 | C11: =B11*FC_AMT -> 9312200 | D11: =USD_FWD -> 9325898.1 | E11: =USD_MM -> 9325898.1 | F11: =MAX(B11,K_PUT)*FC_AMT+FV_PREM_PUT -> 9137369.6 | G11: =MIN(B11,K_CALL)*FC_AMT+FV_PREM_CALL -> 8939271.5 | H11: =D11-C11 -> 13698.126 | I11: =E11-C11 -> 13698.126 | J11: =F11-C11 -> -174830.37 | K11: =IF(C11=MAX(C11,D11,E11,F11),"No Hedge",IF(D11=MAX(C11,D11,E11,F11),"Forward",IF(E11=MAX(C11,D11,E11,F11),"Money Market","Put"))) -> Forward | L11: =IF(D11=MAX(D11,E11,F11),"Forward",IF(E11=MAX(D11,E11,F11),"Money Market","Put")) -> Forward
A12: 2 | B12: =S0_in*(1+A12*STEP_FRAC) -> 1.17555 | C12: =B12*FC_AMT -> 9404400 | D12: =USD_FWD -> 9325898.1 | E12: =USD_MM -> 9325898.1 | F12: =MAX(B12,K_PUT)*FC_AMT+FV_PREM_PUT -> 9229569.6 | G12: =MIN(B12,K_CALL)*FC_AMT+FV_PREM_CALL -> 8939271.5 | H12: =D12-C12 -> -78501.874 | I12: =E12-C12 -> -78501.874 | J12: =F12-C12 -> -174830.37 | K12: =IF(C12=MAX(C12,D12,E12,F12),"No Hedge",IF(D12=MAX(C12,D12,E12,F12),"Forward",IF(E12=MAX(C12,D12,E12,F12),"Money Market","Put"))) -> No Hedge | L12: =IF(D12=MAX(D12,E12,F12),"Forward",IF(E12=MAX(D12,E12,F12),"Money Market","Put")) -> Forward
A13: 3 | B13: =S0_in*(1+A13*STEP_FRAC) -> 1.187075 | C13: =B13*FC_AMT -> 9496600 | D13: =USD_FWD -> 9325898.1 | E13: =USD_MM -> 9325898.1 | F13: =MAX(B13,K_PUT)*FC_AMT+FV_PREM_PUT -> 9321769.6 | G13: =MIN(B13,K_CALL)*FC_AMT+FV_PREM_CALL -> 8939271.5 | H13: =D13-C13 -> -170701.87 | I13: =E13-C13 -> -170701.87 | J13: =F13-C13 -> -174830.37 | K13: =IF(C13=MAX(C13,D13,E13,F13),"No Hedge",IF(D13=MAX(C13,D13,E13,F13),"Forward",IF(E13=MAX(C13,D13,E13,F13),"Money Market","Put"))) -> No Hedge | L13: =IF(D13=MAX(D13,E13,F13),"Forward",IF(E13=MAX(D13,E13,F13),"Money Market","Put")) -> Forward
A14: 4 | B14: =S0_in*(1+A14*STEP_FRAC) -> 1.1986 | C14: =B14*FC_AMT -> 9588800 | D14: =USD_FWD -> 9325898.1 | E14: =USD_MM -> 9325898.1 | F14: =MAX(B14,K_PUT)*FC_AMT+FV_PREM_PUT -> 9413969.6 | G14: =MIN(B14,K_CALL)*FC_AMT+FV_PREM_CALL -> 8939271.5 | H14: =D14-C14 -> -262901.87 | I14: =E14-C14 -> -262901.87 | J14: =F14-C14 -> -174830.37 | K14: =IF(C14=MAX(C14,D14,E14,F14),"No Hedge",IF(D14=MAX(C14,D14,E14,F14),"Forward",IF(E14=MAX(C14,D14,E14,F14),"Money Market","Put"))) -> No Hedge | L14: =IF(D14=MAX(D14,E14,F14),"Forward",IF(E14=MAX(D14,E14,F14),"Money Market","Put")) -> Put
A15: 5 | B15: =S0_in*(1+A15*STEP_FRAC) -> 1.210125 | C15: =B15*FC_AMT -> 9681000 | D15: =USD_FWD -> 9325898.1 | E15: =USD_MM -> 9325898.1 | F15: =MAX(B15,K_PUT)*FC_AMT+FV_PREM_PUT -> 9506169.6 | G15: =MIN(B15,K_CALL)*FC_AMT+FV_PREM_CALL -> 8939271.5 | H15: =D15-C15 -> -355101.87 | I15: =E15-C15 -> -355101.87 | J15: =F15-C15 -> -174830.37 | K15: =IF(C15=MAX(C15,D15,E15,F15),"No Hedge",IF(D15=MAX(C15,D15,E15,F15),"Forward",IF(E15=MAX(C15,D15,E15,F15),"Money Market","Put"))) -> No Hedge | L15: =IF(D15=MAX(D15,E15,F15),"Forward",IF(E15=MAX(D15,E15,F15),"Money Market","Put")) -> Put
A17: Grid check: mean(S_T) should equal S0_in (symmetry)
A18: Grid symmetry check | C18: =IF(ABS((MIN(B5:B15)+MAX(B5:B15))/2-S0_in)<0.0001,"PASS","FAIL") -> PASS

Sheet Notes-Validation
A1: Notes, Assumptions & Validation
A2: Data sources, modeling conventions, and the Phase-3 audit checklist
A4: Validation Checks (Spec §7)
A5: Check | B5: Result | C5: Formula source
A6: Parity check: USD_MM ties to USD_FWD within 0.05% | B6: =MoneyMarket!C16 -> PASS | C6: MoneyMarket tab
A7: Put kink check at S_T = K_PUT | B7: =Options_Put!C13 -> PASS | C7: Options_Put tab
A8: Sensitivity grid symmetric around S0_in, driven by STEP_FRAC | B8: =Sensitivity!C18 -> PASS | C8: Sensitivity tab
A9: No formula errors anywhere in the workbook | B9: PASS | C9: Verified via scripts/recalc.py (LibreOffice recalculation) at build time
A10: Every calculated cell is a formula referencing named ranges (no hard-coded results, no bare cell refs) | B10: PASS | C10: Manual review — see analysis/2026-08-07-Badua-build-audit.md
A12: Assumptions & Constraints
A13: • Quote convention: all rates USD per EUR; a higher quote means EUR appreciation.
A14: • Horizon: single-maturity model, T_DAYS = 365.
A15: • Day-count basis: DF_USD uses BASIS_USD = 360 (ACT/360); DF_FC uses BASIS_FC = 365 (ACT/365), split from the outset.
A16: • Parity: the money-market hedge is assumed to replicate the forward hedge under covered interest-rate parity.
A17: • Option premium: paid upfront in USD, quoted per 1 unit of EUR; carried forward at R_USD to settlement.
A18: • Counterparty / credit risk excluded; all derivatives assumed frictionless and creditworthy.
A19: • Transaction costs and bid-ask spreads excluded from the base case.
A20: • Tax / accounting treatment excluded — pre-tax cash outcomes only.
A21: • S_T is varied deterministically across the grid; no probability weights or implied-volatility distribution applied.
A22: • K_CALL / PREM_CALL are indicative placeholders added for build-contract completeness; the exposure is receivable-only and the call family is not part of the recommendation.
A24: Change Log
A25: Version | B25: Date | C25: Author | D25: Change
A26: 1.0 | B26: 2026-08-07 | C26: Allan Jay Badua | D26: Initial workbook build from docs/specs/2026-08-07-Badua-pharma-exporter-spec.md. AI-assisted (Claude) generation, hand-audited — see analysis/2026-08-07-Badua-build-audit.md and prompt-log.md.
A27: 1.1 | B27: 2026-08-07 | C27: Allan Jay Badua | D27: Phase 4: replaced placeholder inputs (S0_in, R_USD, R_FC, K_PUT, K_CALL) with live market data retrieved 2026-08-07; PREM_PUT retained as scenario assumption; F0_in remains CIP-derived (no live outright forward quote found in free sources). Cross-checked against the FX Hedging Lab (adamwstauffer.github.io/ai-lms/fxlab.html): its uniform T/360 day-count convention vs. this workbook's ACT/360-USD/ACT/365-EUR split produces a reconciled ~$3,629 (0.039%) difference on USD_FWD/USD_MM at live inputs — both tools internally parity-consistent, no workbook change needed. See data/2026-08-07-Badua-market-data.md for full resolution.
